parapara/__init__.py
parapara/generator.py
parapara/version.py
parapara_anime-0.1.0.dist-info/licenses/LICENSE
parapara_anime-0.1.0.dist-info/METADATA
parapara_anime-0.1.0.dist-info/WHEEL
parapara_anime-0.1.0.dist-info/top_level.txt
parapara_anime-0.1.0.dist-info/RECORD
