Metadata-Version: 2.4
Name: parapara-anime
Version: 0.1.0
Summary: parapara-anime: This is a helper for creating a movie of a series of images.
Home-page: https://github.com/siruku6/parapara-anime
Download-URL: https://github.com/siruku6/parapara-anime
Author: siruku6
Author-email: sirukufarios@gmail.com
Maintainer: siruku6
Maintainer-email: sirukufarios@gmail.com
License: MIT License
Classifier: Development Status :: 3 - Alpha
Classifier: Intended Audience :: Developers
Classifier: License :: OSI Approved :: MIT License
Classifier: Programming Language :: Python :: 3
Classifier: Programming Language :: Python :: 3.9
Classifier: Programming Language :: Python :: 3.10
Classifier: Programming Language :: Python :: 3.11
Classifier: Programming Language :: Python :: 3.12
Classifier: Programming Language :: Python :: 3 :: Only
Classifier: Topic :: Software Development :: Libraries :: Python Modules
Classifier: Framework :: Matplotlib
Requires-Python: >=3.8
License-File: LICENSE
Requires-Dist: IPython>=7.23.1
Requires-Dist: matplotlib>=3.0.0
Requires-Dist: numpy>=1.15
Requires-Dist: pyvirtualdisplay>=3.0
Requires-Dist: tqdm>=4.66.0
Provides-Extra: tutorial
Dynamic: author
Dynamic: author-email
Dynamic: classifier
Dynamic: description
Dynamic: description-content-type
Dynamic: download-url
Dynamic: home-page
Dynamic: license
Dynamic: license-file
Dynamic: maintainer
Dynamic: maintainer-email
Dynamic: provides-extra
Dynamic: requires-dist
Dynamic: requires-python
Dynamic: summary
